utils/__init__.py
utils/decode.py
utils/encode.py
utils/list.py
utils_azr-0.0.1.dist-info/LICENSE
utils_azr-0.0.1.dist-info/METADATA
utils_azr-0.0.1.dist-info/WHEEL
utils_azr-0.0.1.dist-info/top_level.txt
utils_azr-0.0.1.dist-info/RECORD
